s1acker/__init__.py
s1acker/cli.py
s1acker/s1acker.py
s1acker-0.1.1.dist-info/DESCRIPTION.rst
s1acker-0.1.1.dist-info/METADATA
s1acker-0.1.1.dist-info/RECORD
s1acker-0.1.1.dist-info/WHEEL
s1acker-0.1.1.dist-info/entry_points.txt
s1acker-0.1.1.dist-info/metadata.json
s1acker-0.1.1.dist-info/top_level.txt
